j2docker/__init__.py
j2docker/cli.py
j2docker/j2docker.py
j2docker-0.1.0.dist-info/DESCRIPTION.rst
j2docker-0.1.0.dist-info/METADATA
j2docker-0.1.0.dist-info/RECORD
j2docker-0.1.0.dist-info/WHEEL
j2docker-0.1.0.dist-info/entry_points.txt
j2docker-0.1.0.dist-info/metadata.json
j2docker-0.1.0.dist-info/top_level.txt
