Metadata-Version: 2.0
Name: j2docker
Version: 0.1.0
Summary: Basiccc templating for Dockerfiles
Home-page: https://github.com/ryanolson/j2docker
Author: Ryan Olson
Author-email: rmolson@gmail.com
License: MIT license
Keywords: j2docker
Platform: UNKNOWN
Classifier: Development Status :: 2 - Pre-Alpha
Classifier: Intended Audience :: Developers
Classifier: License :: OSI Approved :: MIT License
Classifier: Natural Language :: English
Classifier: Programming Language :: Python :: 2
Classifier: Programming Language :: Python :: 2.6
Classifier: Programming Language :: Python :: 2.7
Classifier: Programming Language :: Python :: 3
Classifier: Programming Language :: Python :: 3.3
Classifier: Programming Language :: Python :: 3.4
Classifier: Programming Language :: Python :: 3.5
Requires-Dist: Click (>=6.0)
Requires-Dist: PyYAML (>=3.12)
